botmark/__init__.py
botmark/config.py
botmark/core.py
botmark/markdown_parser/__init__.py
botmark/markdown_parser/parser.py
botmark/markdown_parser/renderer/__init__.py
botmark/markdown_parser/renderer/_vendor/__init__.py
botmark/markdown_parser/renderer/_vendor/markdown_it/__init__.py
botmark/markdown_parser/renderer/_vendor/markdown_it/_compat.py
botmark/markdown_parser/renderer/_vendor/markdown_it/_punycode.py
botmark/markdown_parser/renderer/_vendor/markdown_it/main.py
botmark/markdown_parser/renderer/_vendor/markdown_it/parser_block.py
botmark/markdown_parser/renderer/_vendor/markdown_it/parser_core.py
botmark/markdown_parser/renderer/_vendor/markdown_it/parser_inline.py
botmark/markdown_parser/renderer/_vendor/markdown_it/py.typed
botmark/markdown_parser/renderer/_vendor/markdown_it/renderer.py
botmark/markdown_parser/renderer/_vendor/markdown_it/ruler.py
botmark/markdown_parser/renderer/_vendor/markdown_it/token.py
botmark/markdown_parser/renderer/_vendor/markdown_it/tree.py
botmark/markdown_parser/renderer/_vendor/markdown_it/utils.py
botmark/markdown_parser/renderer/_vendor/markdown_it/cli/__init__.py
botmark/markdown_parser/renderer/_vendor/markdown_it/cli/parse.py
botmark/markdown_parser/renderer/_vendor/markdown_it/common/__init__.py
botmark/markdown_parser/renderer/_vendor/markdown_it/common/entities.py
botmark/markdown_parser/renderer/_vendor/markdown_it/common/html_blocks.py
botmark/markdown_parser/renderer/_vendor/markdown_it/common/html_re.py
botmark/markdown_parser/renderer/_vendor/markdown_it/common/normalize_url.py
botmark/markdown_parser/renderer/_vendor/markdown_it/common/utils.py
botmark/markdown_parser/renderer/_vendor/markdown_it/helpers/__init__.py
botmark/markdown_parser/renderer/_vendor/markdown_it/helpers/parse_link_destination.py
botmark/markdown_parser/renderer/_vendor/markdown_it/helpers/parse_link_label.py
botmark/markdown_parser/renderer/_vendor/markdown_it/helpers/parse_link_title.py
botmark-1.1.19.dist-info/licenses/LICENSE
botmark-1.1.19.dist-info/METADATA
botmark-1.1.19.dist-info/WHEEL
botmark-1.1.19.dist-info/top_level.txt
botmark-1.1.19.dist-info/RECORD
