Metadata-Version: 2.4
Name: botmark
Version: 1.1.19
Summary: BotMark – Define, run, and document LLM chatbots in plain Markdown. Framework for executable, portable, and LLM-agnostic chatbot workflows.
Home-page: https://www.radiox-innovation.de/
Author: Frank Rettig
Author-email: 118481987+frettig-radiox@users.noreply.github.com
License: MIT
Classifier: Operating System :: OS Independent
Classifier: Programming Language :: Python :: 3
Classifier: Programming Language :: Python :: 3 :: Only
Classifier: Programming Language :: Python :: 3.11
Requires-Python: >=3.11
License-File: LICENSE
Requires-Dist: pydantic-ai-slim>=0.4.8
Requires-Dist: openai-agents
Provides-Extra: remote-files
Requires-Dist: requests>=2.32.4; extra == "remote-files"
Provides-Extra: jinja2
Requires-Dist: Jinja2>=3.1.6; extra == "jinja2"
Provides-Extra: mako
Requires-Dist: Mako>=1.3.10; extra == "mako"
Provides-Extra: templates
Requires-Dist: Jinja2>=3.1.6; extra == "templates"
Requires-Dist: Mako>=1.3.10; extra == "templates"
Provides-Extra: dotenv
Requires-Dist: python-dotenv>=1.1.1; extra == "dotenv"
Provides-Extra: pydantic-ai
Requires-Dist: pydantic-ai[all]>=0.4.8; extra == "pydantic-ai"
Provides-Extra: pydantic
Requires-Dist: pydantic; extra == "pydantic"
Provides-Extra: logfire
Requires-Dist: pydantic-ai-slim[logfire]>=0.4.8; extra == "logfire"
Provides-Extra: evals
Requires-Dist: pydantic-ai-slim[evals]>=0.4.8; extra == "evals"
Provides-Extra: openai
Requires-Dist: pydantic-ai-slim[openai]>=0.4.8; extra == "openai"
Provides-Extra: vertexai
Requires-Dist: pydantic-ai-slim[vertexai]>=0.4.8; extra == "vertexai"
Provides-Extra: google
Requires-Dist: pydantic-ai-slim[google]>=0.4.8; extra == "google"
Provides-Extra: anthropic
Requires-Dist: pydantic-ai-slim[anthropic]>=0.4.8; extra == "anthropic"
Provides-Extra: groq
Requires-Dist: pydantic-ai-slim[groq]>=0.4.8; extra == "groq"
Provides-Extra: mistral
Requires-Dist: pydantic-ai-slim[mistral]>=0.4.8; extra == "mistral"
Provides-Extra: cohere
Requires-Dist: pydantic-ai-slim[cohere]>=0.4.8; extra == "cohere"
Provides-Extra: bedrock
Requires-Dist: pydantic-ai-slim[bedrock]>=0.4.8; extra == "bedrock"
Provides-Extra: huggingface
Requires-Dist: pydantic-ai-slim[huggingface]>=0.4.8; extra == "huggingface"
Provides-Extra: duckduckgo
Requires-Dist: pydantic-ai-slim[duckduckgo]>=0.4.8; extra == "duckduckgo"
Provides-Extra: tavily
Requires-Dist: pydantic-ai-slim[tavily]>=0.4.8; extra == "tavily"
Provides-Extra: cli
Requires-Dist: pydantic-ai-slim[cli]>=0.4.8; extra == "cli"
Provides-Extra: mcp
Requires-Dist: pydantic-ai-slim[mcp]>=0.4.8; extra == "mcp"
Provides-Extra: a2a
Requires-Dist: pydantic-ai-slim[a2a]>=0.4.8; extra == "a2a"
Provides-Extra: ag-ui
Requires-Dist: pydantic-ai-slim[ag-ui]>=0.4.8; extra == "ag-ui"
Provides-Extra: all
Requires-Dist: Jinja2>=3.1.6; extra == "all"
Requires-Dist: Mako>=1.3.10; extra == "all"
Requires-Dist: python-dotenv>=1.1.1; extra == "all"
Requires-Dist: requests>=2.32.4; extra == "all"
Requires-Dist: pydantic; extra == "all"
Requires-Dist: pydantic-ai-slim[logfire]>=0.4.8; extra == "all"
Requires-Dist: pydantic-ai-slim[evals]>=0.4.8; extra == "all"
Requires-Dist: pydantic-ai-slim[openai]>=0.4.8; extra == "all"
Requires-Dist: pydantic-ai-slim[vertexai]>=0.4.8; extra == "all"
Requires-Dist: pydantic-ai-slim[google]>=0.4.8; extra == "all"
Requires-Dist: pydantic-ai-slim[anthropic]>=0.4.8; extra == "all"
Requires-Dist: pydantic-ai-slim[groq]>=0.4.8; extra == "all"
Requires-Dist: pydantic-ai-slim[mistral]>=0.4.8; extra == "all"
Requires-Dist: pydantic-ai-slim[cohere]>=0.4.8; extra == "all"
Requires-Dist: pydantic-ai-slim[bedrock]>=0.4.8; extra == "all"
Requires-Dist: pydantic-ai-slim[huggingface]>=0.4.8; extra == "all"
Requires-Dist: pydantic-ai-slim[duckduckgo]>=0.4.8; extra == "all"
Requires-Dist: pydantic-ai-slim[tavily]>=0.4.8; extra == "all"
Requires-Dist: pydantic-ai-slim[cli]>=0.4.8; extra == "all"
Requires-Dist: pydantic-ai-slim[mcp]>=0.4.8; extra == "all"
Requires-Dist: pydantic-ai-slim[a2a]>=0.4.8; extra == "all"
Requires-Dist: pydantic-ai-slim[ag-ui]>=0.4.8; extra == "all"
Dynamic: author
Dynamic: author-email
Dynamic: classifier
Dynamic: description
Dynamic: description-content-type
Dynamic: home-page
Dynamic: license
Dynamic: license-file
Dynamic: provides-extra
Dynamic: requires-dist
Dynamic: requires-python
Dynamic: summary
